MOODS/__init__.py
MOODS/_parsers.cpython-311-darwin.so
MOODS/_scan.cpython-311-darwin.so
MOODS/_tools.cpython-311-darwin.so
MOODS/misc.py
MOODS/parsers.py
MOODS/scan.py
MOODS/tools.py
mira_moods-1.9.4.2.data/scripts/moods-dna.py
mira_moods-1.9.4.2.dist-info/COPYING.BIOPYTHON
mira_moods-1.9.4.2.dist-info/COPYING.GPLv3
mira_moods-1.9.4.2.dist-info/METADATA
mira_moods-1.9.4.2.dist-info/WHEEL
mira_moods-1.9.4.2.dist-info/top_level.txt
mira_moods-1.9.4.2.dist-info/RECORD
