Metadata-Version: 2.1
Name: mira-moods
Version: 1.9.4.2
Summary: MOODS: Motif Occurrence Detection Suite
Home-page: https://www.cs.helsinki.fi/group/pssmfind/
Maintainer: Janne H. Korhonen
Maintainer-email: janne.h.korhonen@gmail.com
License: GPLv3 / Biopython license
Keywords: PWM,PSSM,motif scan
Classifier: Topic :: Scientific/Engineering :: Bio-Informatics
Requires-Python: >=3.6
License-File: COPYING.BIOPYTHON
License-File: COPYING.GPLv3
